{
    "firstName": "testString",
    "lastName": "testString",
    "email": "thneed@pm.me",
    "confirmEmail": "thneed@pm.me",
    "jobTitle": "testString",
    "companyType": "testString",
    "address": "testString",
    "city": "testString",
    "state": "testString",
    "zip": "02090",
    "country": "testString",
    "phone": "testString",
    "arrivalDate": "2022-10-31T09:00:00Z",
    "departureDate": "2022-11-25T09:00:00Z",
    "firstTime": true,
    "newcomers": true,
    "stayAtHotel": true
}